ccz/__init__.py
ccz-0.3.2.dist-info/METADATA
ccz-0.3.2.dist-info/WHEEL
ccz-0.3.2.dist-info/entry_points.txt
ccz-0.3.2.dist-info/top_level.txt
ccz-0.3.2.dist-info/RECORD
