Metadata-Version: 2.1
Name: ccz
Version: 0.3.2
Summary: UNKNOWN
Home-page: UNKNOWN
License: UNKNOWN
Platform: UNKNOWN
Requires-Python: >=3.6
Requires-Dist: ccxt
